mtn_oauth_v1/__init__.py
mtn_oauth_v1/_base_client.py
mtn_oauth_v1/_client.py
mtn_oauth_v1/_compat.py
mtn_oauth_v1/_constants.py
mtn_oauth_v1/_exceptions.py
mtn_oauth_v1/_files.py
mtn_oauth_v1/_models.py
mtn_oauth_v1/_qs.py
mtn_oauth_v1/_resource.py
mtn_oauth_v1/_response.py
mtn_oauth_v1/_streaming.py
mtn_oauth_v1/_types.py
mtn_oauth_v1/_version.py
mtn_oauth_v1/py.typed
mtn_oauth_v1/_utils/__init__.py
mtn_oauth_v1/_utils/_logs.py
mtn_oauth_v1/_utils/_proxy.py
mtn_oauth_v1/_utils/_reflection.py
mtn_oauth_v1/_utils/_streams.py
mtn_oauth_v1/_utils/_sync.py
mtn_oauth_v1/_utils/_transform.py
mtn_oauth_v1/_utils/_typing.py
mtn_oauth_v1/_utils/_utils.py
mtn_oauth_v1/lib/.keep
mtn_oauth_v1/resources/__init__.py
mtn_oauth_v1/resources/access_tokens.py
mtn_oauth_v1/types/__init__.py
mtn_oauth_v1/types/access_token_create_params.py
mtn_oauth_v1/types/successtoken.py
mtn_oauth_v1-0.1.0a2.dist-info/METADATA
mtn_oauth_v1-0.1.0a2.dist-info/WHEEL
mtn_oauth_v1-0.1.0a2.dist-info/licenses/LICENSE
mtn_oauth_v1-0.1.0a2.dist-info/RECORD
